bytedance_workflow123/__init__.py
bytedance_workflow123-0.0.1.dist-info/METADATA
bytedance_workflow123-0.0.1.dist-info/WHEEL
bytedance_workflow123-0.0.1.dist-info/top_level.txt
bytedance_workflow123-0.0.1.dist-info/RECORD
